youtil/yt.py
youtil-1.0.2.dist-info/METADATA
youtil-1.0.2.dist-info/WHEEL
youtil-1.0.2.dist-info/top_level.txt
youtil-1.0.2.dist-info/RECORD
