Metadata-Version: 2.1
Name: youtil
Version: 1.0.2
Summary: Module to get youtube details
Home-page: https://github.com/smartwe/youtil
Author: smartwe
Author-email: sparklingwee@naver.com
License: MIT
Platform: UNKNOWN
Requires-Python: >=3
Requires-Dist: bs4
